intake_bluesky/__init__.py
intake_bluesky/_version.py
intake_bluesky/core.py
intake_bluesky/in_memory.py
intake_bluesky/jsonl.py
intake_bluesky/mongo_embedded.py
intake_bluesky/mongo_normalized.py
intake_bluesky/msgpack.py
intake_bluesky/tests/__init__.py
intake_bluesky/tests/conftest.py
intake_bluesky/tests/fixtures.py
intake_bluesky/tests/generic.py
intake_bluesky/tests/test_core.py
intake_bluesky/tests/test_dask_filler.py
intake_bluesky/tests/test_jsonl.py
intake_bluesky/tests/test_mongo_embedded.py
intake_bluesky/tests/test_mongo_normalized.py
intake_bluesky/tests/test_msgpack.py
intake_bluesky-0.1.0a10.dist-info/METADATA
intake_bluesky-0.1.0a10.dist-info/RECORD
intake_bluesky-0.1.0a10.dist-info/WHEEL
intake_bluesky-0.1.0a10.dist-info/entry_points.txt
intake_bluesky-0.1.0a10.dist-info/top_level.txt
