Metadata-Version: 2.1
Name: intake-bluesky
Version: 0.1.0a10
Summary: Bridge between intake and bluesky's event model
Home-page: https://github.com/NSLS-II/intake-bluesky
Author: Brookhaven National Lab
Author-email: dallan@bnl.gov
License: BSD (3-clause)
Platform: UNKNOWN
Classifier: Development Status :: 2 - Pre-Alpha
Classifier: Natural Language :: English
Classifier: Programming Language :: Python :: 3
Requires-Python: >=3.6
Requires-Dist: dask[bag]
Requires-Dist: event-model (>=1.11.1b1)
Requires-Dist: msgpack
Requires-Dist: msgpack-numpy
Requires-Dist: intake (!=0.5.0)
Requires-Dist: intake-xarray
Requires-Dist: mongoquery
Requires-Dist: msgpack
Requires-Dist: msgpack-numpy
Requires-Dist: numpy
Requires-Dist: pandas
Requires-Dist: pymongo
Requires-Dist: pyyaml
Requires-Dist: requests
Requires-Dist: xarray
